libpastelid.cpython-312-x86_64-linux-gnu.so
libpastelid-0.4.dist-info/WHEEL
libpastelid-0.4.dist-info/top_level.txt
libpastelid-0.4.dist-info/METADATA
libpastelid-0.4.dist-info/RECORD
