Metadata-Version: 2.1
Name: libpastelid
Version: 0.4
Summary: Python bindings for the libpastelid C++ library - PastelID signer/verifier
Author-email: alexey@pastel.network
Classifier: Programming Language :: Python :: 3
Classifier: Programming Language :: Python :: 3.10
Classifier: License :: OSI Approved :: MIT License
Classifier: Operating System :: POSIX :: Linux
Requires-Python: >=3.9
